aedev/project_vars.py
aedev_project_vars-0.3.5.dist-info/licenses/LICENSE.md
aedev_project_vars-0.3.5.dist-info/METADATA
aedev_project_vars-0.3.5.dist-info/WHEEL
aedev_project_vars-0.3.5.dist-info/top_level.txt
aedev_project_vars-0.3.5.dist-info/zip-safe
aedev_project_vars-0.3.5.dist-info/RECORD
