Metadata-Version: 2.4
Name: aedev_project_vars
Version: 0.3.5
Summary: aedev namespace module portion project_vars: project development variables
Home-page: https://gitlab.com/aedev-group/aedev_project_vars
Author: AndiEcker
Author-email: aecker2@gmail.com
License: GPL-3.0-or-later
Project-URL: Bug Tracker, https://gitlab.com/aedev-group/aedev_project_vars/-/issues
Project-URL: Documentation, https://aedev.readthedocs.io/en/latest/_autosummary/aedev.project_vars.html
Project-URL: Repository, https://gitlab.com/aedev-group/aedev_project_vars
Project-URL: Source, https://aedev.readthedocs.io/en/latest/_modules/aedev/project_vars.html
Keywords: configuration,development,environment,productivity
Classifier: Development Status :: 3 - Alpha
Classifier: Natural Language :: English
Classifier: Operating System :: OS Independent
Classifier: Programming Language :: Python
Classifier: Programming Language :: Python :: 3
Classifier: Programming Language :: Python :: 3.12
Classifier: Topic :: Software Development :: Libraries :: Python Modules
Classifier: Typing :: Typed
Requires-Python: >=3.12
License-File: LICENSE.md
Requires-Dist: ae_base
Requires-Dist: ae_paths
Requires-Dist: ae_core
Requires-Dist: ae_shell
Requires-Dist: ae_managed_files
Requires-Dist: aedev_base
Requires-Dist: aedev_commands
Provides-Extra: dev
Requires-Dist: aedev_project_tpls; extra == "dev"
Requires-Dist: aedev_aedev; extra == "dev"
Requires-Dist: anybadge; extra == "dev"
Requires-Dist: coverage-badge; extra == "dev"
Requires-Dist: flake8; extra == "dev"
Requires-Dist: mypy; extra == "dev"
Requires-Dist: pylint; extra == "dev"
Requires-Dist: pytest; extra == "dev"
Requires-Dist: pytest-cov; extra == "dev"
Requires-Dist: pytest-django; extra == "dev"
Requires-Dist: typing; extra == "dev"
Requires-Dist: types-setuptools; extra == "dev"
Provides-Extra: docs
Provides-Extra: tests
Requires-Dist: anybadge; extra == "tests"
Requires-Dist: coverage-badge; extra == "tests"
Requires-Dist: flake8; extra == "tests"
Requires-Dist: mypy; extra == "tests"
Requires-Dist: pylint; extra == "tests"
Requires-Dist: pytest; extra == "tests"
Requires-Dist: pytest-cov; extra == "tests"
Requires-Dist: pytest-django; extra == "tests"
Requires-Dist: typing; extra == "tests"
Requires-Dist: types-setuptools; extra == "tests"
Dynamic: author
Dynamic: author-email
Dynamic: classifier
Dynamic: description
Dynamic: description-content-type
Dynamic: home-page
Dynamic: keywords
Dynamic: license
Dynamic: license-file
Dynamic: project-url
Dynamic: provides-extra
Dynamic: requires-dist
Dynamic: requires-python
Dynamic: summary
